poetry_demo/__init__.py
poetry_demo_muhammad_hamza-0.1.0.dist-info/METADATA
poetry_demo_muhammad_hamza-0.1.0.dist-info/WHEEL
poetry_demo_muhammad_hamza-0.1.0.dist-info/RECORD
